discord_error_handling/__init__.py
discord_error_handle-0.0.1.dist-info/LICENSE
discord_error_handle-0.0.1.dist-info/METADATA
discord_error_handle-0.0.1.dist-info/WHEEL
discord_error_handle-0.0.1.dist-info/top_level.txt
discord_error_handle-0.0.1.dist-info/RECORD
