Metadata-Version: 2.1
Name: discord-error-handle
Version: 0.0.1
Summary: A package that converts all things in a list into either string or int
Home-page: https://github.com/Ricardolcm888/discord_error_handle
Author: Ricardolcm
License: UNKNOWN
Platform: UNKNOWN
Classifier: Programming Language :: Python :: 3
Classifier: License :: OSI Approved :: MIT License
Classifier: Operating System :: OS Independent
Requires-Python: >=3.6
